obv_fab_deploy/__init__.py
obv_fab_deploy/lakehouse.py
obv_fab_deploy/notebook.py
obv_fab_deploy/pipeline.py
obv_fab_deploy/report.py
obv_fab_deploy/semantic_model.py
obv_fab_deploy/utils.py
obv_fab_deploy-0.1.4.dist-info/licenses/LICENSE
obv_fab_deploy-0.1.4.dist-info/METADATA
obv_fab_deploy-0.1.4.dist-info/WHEEL
obv_fab_deploy-0.1.4.dist-info/top_level.txt
obv_fab_deploy-0.1.4.dist-info/RECORD
