Metadata-Version: 2.4
Name: obv-fab-deploy
Version: 0.1.4
Summary: Unofficial Microsoft Fabric deployment toolkit by Obvience
Author-email: Andre Fomin <you@example.com>
License-Expression: MIT
Requires-Python: >=3.10
License-File: LICENSE
Requires-Dist: requests
Requires-Dist: pandas
Dynamic: license-file
